aoai/__init__.py
aoai/executor.py
aoai/profile.py
aoai_api_wrapper-0.1.0.dist-info/METADATA
aoai_api_wrapper-0.1.0.dist-info/WHEEL
aoai_api_wrapper-0.1.0.dist-info/RECORD
